Topsis_102103283_102103283/Topsis.py
Topsis_102103283_102103283/__init__.py
Topsis_Raghav_102103283-0.7.dist-info/METADATA
Topsis_Raghav_102103283-0.7.dist-info/WHEEL
Topsis_Raghav_102103283-0.7.dist-info/entry_points.txt
Topsis_Raghav_102103283-0.7.dist-info/top_level.txt
Topsis_Raghav_102103283-0.7.dist-info/RECORD
