Metadata-Version: 2.1
Name: Topsis-Raghav-102103283
Version: 0.7
Summary: Topsis package python
Author: Raghav Garg
Author-email: rgarg5_be21@thapar.edu
License: MIT
Keywords: Python,Topsis,102103283
Classifier: Development Status :: 4 - Beta
Classifier: Intended Audience :: Developers
Classifier: Topic :: Software Development :: Build Tools
Classifier: License :: OSI Approved :: MIT License
Classifier: Programming Language :: Python :: 3
Classifier: Programming Language :: Python :: 3.4
Classifier: Programming Language :: Python :: 3.5
Classifier: Programming Language :: Python :: 3.6
Requires-Dist: validators
Requires-Dist: beautifulsoup4
